{
  "parent": "minecraft:recipes/root",
  "rewards": {
    "recipes": [
      "minecraft:big_cannon_sheet_inexpensive"
    ]
  },
  "criteria": {
    "has_inexpensive_big_cartridge_sheet": {
      "trigger": "minecraft:inventory_changed",
      "conditions": {
        "items": [
          {
            "tag": "createbigcannons:inexpensive_big_cartridge_sheet"
          }
        ]
      }
    },
    "has_the_recipe": {
      "trigger": "minecraft:recipe_unlocked",
      "conditions": {
        "recipe": "minecraft:big_cannon_sheet_inexpensive"
      }
    }
  },
  "requirements": [
    [
      "has_inexpensive_big_cartridge_sheet",
      "has_the_recipe"
    ]
  ]
}